{
	"name": "relationship-pzdzubkfvt",
	"properties": {
		"Namespace": {
			"DatabaseName": "Retail_ggi"
		},
		"Origin": {
			"Type": "SPARK"
		},
		"FromTableName": "Shipment",
		"ToTableName": "ServiceRequestReason",
		"ColumnRelationshipInformations": [
			{
				"FromColumnName": "ShipmentId",
				"ToColumnName": "ShipmentId"
			}
		],
		"Properties": {
			"DerivedModelRelationshipInfo": "{\"baseRelationship\":{\"fromEntity\":\"Shipment.cdm.json/Shipment\",\"toEntity\":\"ServiceRequestReason.cdm.json/ServiceRequestReason\",\"joinPairs\":[{\"fromAttribute\":\"ShipmentId\",\"toAttribute\":\"ShipmentId\"}]}}"
		},
		"PublishStatus": "PUBLISHED",
		"ObjectVersion": 1,
		"ObjectId": "0e6ca564-968f-43d0-8954-6466723560b2",
		"Name": "relationship-pzdzubkfvt",
		"EntityType": "RELATIONSHIP"
	},
	"type": "RELATIONSHIP"
}