{
	"name": "relationship-tdrgsburdd",
	"properties": {
		"Namespace": {
			"DatabaseName": "Retail_ggi"
		},
		"Origin": {
			"Type": "SPARK"
		},
		"FromTableName": "Communication",
		"ToTableName": "Document",
		"ColumnRelationshipInformations": [
			{
				"FromColumnName": "CommunicationId",
				"ToColumnName": "DocumentId"
			}
		],
		"Properties": {
			"DerivedModelRelationshipInfo": "{\"baseRelationship\":{\"fromEntity\":\"Communication.cdm.json/Communication\",\"toEntity\":\"Document.cdm.json/Document\",\"joinPairs\":[{\"fromAttribute\":\"CommunicationId\",\"toAttribute\":\"DocumentId\"}]}}"
		},
		"PublishStatus": "PUBLISHED",
		"ObjectVersion": 1,
		"ObjectId": "535d3a4e-1553-4bc0-98a3-51de6f110f21",
		"Name": "relationship-tdrgsburdd",
		"EntityType": "RELATIONSHIP"
	},
	"type": "RELATIONSHIP"
}