{
	"name": "relationship-cenjgbgtal",
	"properties": {
		"Namespace": {
			"DatabaseName": "Retail_ggi"
		},
		"Origin": {
			"Type": "SPARK"
		},
		"FromTableName": "Channel",
		"ToTableName": "Transaction",
		"ColumnRelationshipInformations": [
			{
				"FromColumnName": "ChannelId",
				"ToColumnName": "DistributionChannelId"
			}
		],
		"Properties": {
			"DerivedModelRelationshipInfo": "{\"baseRelationship\":{\"fromEntity\":\"Channel.cdm.json/Channel\",\"toEntity\":\"Transaction.cdm.json/Transaction\",\"joinPairs\":[{\"fromAttribute\":\"ChannelId\",\"toAttribute\":\"DistributionChannelId\"}]}}"
		},
		"PublishStatus": "PUBLISHED",
		"ObjectVersion": 1,
		"ObjectId": "d6406d7e-9588-4c2b-b457-7727326af7ce",
		"Name": "relationship-cenjgbgtal",
		"EntityType": "RELATIONSHIP"
	},
	"type": "RELATIONSHIP"
}